[{
  "_id": {
    "$oid": "6173bed7ce3cd7dfabac333d"
  },
  "fleet_id": "76-759-4870",
  "fleet_time": "1/7/2021",
  "fleet_content": "http://dummyimage.com/218x100.png/cc0000/ffffff",
  "username": {
    "$ref": "User",
    "$id": {
      "$oid": "61739cb1ce3cd7dfabac3326"
    }
  },
  "duration": 1275
},{
  "_id": {
    "$oid": "6173bed7ce3cd7dfabac333e"
  },
  "fleet_id": "01-445-6404",
  "fleet_time": "8/29/2021",
  "fleet_content": "http://dummyimage.com/227x100.png/ff4444/ffffff",
  "username": {
    "$ref": "User",
    "$id": {
      "$oid": "61739cb1ce3cd7dfabac3327"
    }
  },
  "duration": 998
},{
  "_id": {
    "$oid": "6173bed7ce3cd7dfabac333f"
  },
  "fleet_id": "50-716-8995",
  "fleet_time": "3/19/2021",
  "fleet_content": "http://dummyimage.com/222x100.png/dddddd/000000",
  "username": {
    "$ref": "User",
    "$id": {
      "$oid": "61739cb1ce3cd7dfabac3328"
    }
  },
  "duration": 677
},{
  "_id": {
    "$oid": "6173bed7ce3cd7dfabac3340"
  },
  "fleet_id": "80-003-7419",
  "fleet_time": "9/28/2021",
  "fleet_content": "http://dummyimage.com/115x100.png/ff4444/ffffff",
  "username": {
    "$ref": "User",
    "$id": {
      "$oid": "61739cb1ce3cd7dfabac3329"
    }
  },
  "duration": 1029
},{
  "_id": {
    "$oid": "6173bed7ce3cd7dfabac3341"
  },
  "fleet_id": "97-510-8818",
  "fleet_time": "9/5/2021",
  "fleet_content": "http://dummyimage.com/168x100.png/cc0000/ffffff",
  "username": {
    "$ref": "User",
    "$id": {
      "$oid": "61739cb1ce3cd7dfabac332a"
    }
  }
},{
  "_id": {
    "$oid": "6173bed7ce3cd7dfabac3342"
  },
  "fleet_id": "86-747-2269",
  "fleet_time": "7/23/2021",
  "fleet_content": "http://dummyimage.com/199x100.png/5fa2dd/ffffff",
  "username": {
    "$ref": "User",
    "$id": {
      "$oid": "61739cb1ce3cd7dfabac332b"
    }
  },
  "duration": 45
},{
  "_id": {
    "$oid": "6173bed7ce3cd7dfabac3343"
  },
  "fleet_id": "80-054-7172",
  "fleet_time": "4/15/2021",
  "fleet_content": "http://dummyimage.com/142x100.png/cc0000/ffffff",
  "username": {
    "$ref": "User",
    "$id": {
      "$oid": "61739cb1ce3cd7dfabac332c"
    }
  },
  "duration": 488
},{
  "_id": {
    "$oid": "6173bed7ce3cd7dfabac3344"
  },
  "fleet_id": "64-647-4212",
  "fleet_time": "9/1/2021",
  "fleet_content": "http://dummyimage.com/128x100.png/5fa2dd/ffffff",
  "username": {
    "$ref": "User",
    "$id": {
      "$oid": "61739cb1ce3cd7dfabac332d"
    }
  },
  "duration": 318
},{
  "_id": {
    "$oid": "6173bed7ce3cd7dfabac3345"
  },
  "fleet_id": "16-673-2620",
  "fleet_time": "10/20/2021",
  "fleet_content": "http://dummyimage.com/145x100.png/cc0000/ffffff",
  "username": {
    "$ref": "User",
    "$id": {
      "$oid": "61739cb1ce3cd7dfabac332e"
    }
  },
  "duration": 802
},{
  "_id": {
    "$oid": "6173bed7ce3cd7dfabac3346"
  },
  "fleet_id": "25-929-6476",
  "fleet_time": "4/15/2021",
  "fleet_content": "http://dummyimage.com/184x100.png/5fa2dd/ffffff",
  "username": {
    "$ref": "User",
    "$id": {
      "$oid": "61739cb1ce3cd7dfabac332f"
    }
  },
  "duration": 1291
}]